.coveragerc
.gitignore
.travis.yml
CHANGES.rst
COPYRIGHT.txt
HACKING.rst
LICENSE.txt
MANIFEST.in
README.rst
buildout.cfg
example.ini
pytest.ini
setup.py
tox.ini
doc/about.txt
doc/api.txt
doc/changes.txt
doc/conf.py
doc/config.txt
doc/index.txt
src/gocept/__init__.py
src/gocept.jenkinsdsl.egg-info/PKG-INFO
src/gocept.jenkinsdsl.egg-info/SOURCES.txt
src/gocept.jenkinsdsl.egg-info/dependency_links.txt
src/gocept.jenkinsdsl.egg-info/entry_points.txt
src/gocept.jenkinsdsl.egg-info/namespace_packages.txt
src/gocept.jenkinsdsl.egg-info/not-zip-safe
src/gocept.jenkinsdsl.egg-info/requires.txt
src/gocept.jenkinsdsl.egg-info/top_level.txt
src/gocept/jenkinsdsl/__init__.py
src/gocept/jenkinsdsl/jenkinsdsl.py
src/gocept/jenkinsdsl/templates/builder.abstract.groovy
src/gocept/jenkinsdsl/templates/builder.custom.groovy
src/gocept/jenkinsdsl/templates/builder.integration.groovy
src/gocept/jenkinsdsl/templates/builder.matrix.groovy
src/gocept/jenkinsdsl/templates/builder.pytest.groovy
src/gocept/jenkinsdsl/templates/composition.groovy
src/gocept/jenkinsdsl/templates/git.groovy
src/gocept/jenkinsdsl/templates/header.groovy
src/gocept/jenkinsdsl/templates/hg.groovy
src/gocept/jenkinsdsl/templates/interfaces.groovy
src/gocept/jenkinsdsl/templates/jobconfig.groovy
src/gocept/jenkinsdsl/templates/notification.groovy
src/gocept/jenkinsdsl/templates/redmine.groovy
src/gocept/jenkinsdsl/templates/svn.groovy
src/gocept/jenkinsdsl/tests/__init__.py
src/gocept/jenkinsdsl/tests/test_jenkinsdsl.py