Metadata-Version: 2.1
Name: gocept.jenkinsdsl
Version: 1.0
Summary: Create a DSL script for the Jenkins Job DSL plugin from configuration.
Home-page: https://github.com/gocept/gocept.jenkinsdsl
Author: gocept <mail@gocept.com>
Author-email: mail@gocept.com
License: ZPL 2.1
Keywords: jenkins DSL job groovy
Platform: UNKNOWN
Classifier: Development Status :: 4 - Beta
Classifier: License :: OSI Approved :: Zope Public License
Classifier: Programming Language :: Python
Classifier: Programming Language :: Python :: 3
Classifier: Programming Language :: Python :: 3.6
Classifier: Programming Language :: Python :: 3.7
Classifier: Programming Language :: Python :: 3.8
Classifier: Programming Language :: Python :: 3 :: Only
Classifier: Programming Language :: Python :: Implementation :: CPython
Provides-Extra: test
